sot_verify/__init__.py
sot_verify/cli.py
sot_verify-0.1.1.dist-info/METADATA
sot_verify-0.1.1.dist-info/WHEEL
sot_verify-0.1.1.dist-info/entry_points.txt
sot_verify-0.1.1.dist-info/RECORD
